pysak/MyThread.py
pysak/__init__.py
pysak/basic.py
pysak/config.py
pysak/debug.py
pysak/file.py
pysak/img.py
pysak/path.py
pysak/time.py
pysak/user_agent.py
pysak-0.2.0.dist-info/LICENSE
pysak-0.2.0.dist-info/METADATA
pysak-0.2.0.dist-info/WHEEL
pysak-0.2.0.dist-info/top_level.txt
pysak-0.2.0.dist-info/RECORD
