Metadata-Version: 2.1
Name: pysak
Version: 0.2.0
Summary: pysak 是一个简单、强大、干净的python公共函数库。
Home-page: https://github.com/1Gbps/pysak
Author: jaded
Author-email: jaded@foxmail.com
License: UNKNOWN
Platform: UNKNOWN
Classifier: Programming Language :: Python :: 3
Classifier: License :: OSI Approved :: MIT License
Classifier: Operating System :: OS Independent
Requires-Python: >=3.6
